rowdata2file/__init__.py
rowdata2file/__main__.py
rowdata2file/gen_docx.py
rowdata2file/rowdata2docx.py
rowdata2file/rowdata2docx_t.py
rowdata2file/rowdata2file.py
rowdata2file-0.1.1.dist-info/entry_points.txt
rowdata2file-0.1.1.dist-info/LICENSE
rowdata2file-0.1.1.dist-info/WHEEL
rowdata2file-0.1.1.dist-info/METADATA
rowdata2file-0.1.1.dist-info/RECORD
