Metadata-Version: 2.1
Name: rowdata2file
Version: 0.1.1
Summary: Convert rowdata (ag-grid) to a file for python-shell use
Home-page: https://github.com/ffreemt/rowdata2file
License: MIT
Author: ffreemt
Requires-Python: >=3.8.3,<4.0.0
Classifier: License :: OSI Approved :: MIT License
Classifier: Programming Language :: Python :: 3
Classifier: Programming Language :: Python :: 3.9
Classifier: Programming Language :: Python :: 3.10
Requires-Dist: loguru (>=0.6.0,<0.7.0)
Requires-Dist: logzero (>=1.7.0,<2.0.0)
Requires-Dist: python-docx (>=0.8.11,<0.9.0)
Requires-Dist: rich (>=13.3.1,<14.0.0)
Requires-Dist: set-loglevel (>=0.1.2,<0.2.0)
Requires-Dist: typer (>=0.7.0,<0.8.0)
Project-URL: Repository, https://github.com/ffreemt/rowdata2file
